<?xml version="1.0" encoding="UTF-8" standalone="yes"?>
<ad:ad locale="en_US" version="1.11" id="12481583" xmlns:cat="http://www.ebayclassifiedsgroup.com/schema/category/v1" xmlns:rate="http://www.ebayclassifiedsgroup.com/schema/rate/v1" xmlns:reply="http://www.ebayclassifiedsgroup.com/schema/reply/v1" xmlns:ad="http://www.ebayclassifiedsgroup.com/schema/ad/v1" xmlns:loc="http://www.ebayclassifiedsgroup.com/schema/location/v1" xmlns:feed="http://www.ebayclassifiedsgroup.com/schema/feed/v1" xmlns:attr="http://www.ebayclassifiedsgroup.com/schema/attribute/v1" xmlns:pic="http://www.ebayclassifiedsgroup.com/schema/picture/v1" xmlns:types="http://www.ebayclassifiedsgroup.com/schema/types/v1" xmlns:user="http://www.ebayclassifiedsgroup.com/schema/user/v1"><ad:title>Foto y Video Para Bodas</ad:title><ad:description>El día de la boda es uno de los dias más importantes en la vida de una pareja, marca un antes y un después en sus vidas, un día que merece ser recordado!!. 
Le brindamos un servicio fotográfico profesional de su boda: ceremonia, sesión de pareja, fiesta, etc. 
Todas las fotografías estaran en una galeria privada para que miren y escojan para su conveniencia y presupuesto. 
Escríbanos, será un gusto atenderle 
            (571) 288-1100       
[email removed]</ad:description><ad:ad-address><types:street>VA. DC. MD.</types:street><types:city>Manassas</types:city><types:state>VA</types:state><types:zip-code>20109</types:zip-code><types:longitude>-77.683495</types:longitude><types:latitude>39.118313</types:latitude></ad:ad-address><ad:ad-status><ad:value>ACTIVE</ad:value></ad:ad-status><ad:user-id>245386</ad:user-id><ad:poster-ip-address>108.56.241.106</ad:poster-ip-address><ad:poster-machine-id>489b2321-00eb-49e9-abf1-875c517c8a44~130582400e1</ad:poster-machine-id><ad:ad-source-id>POLARIS_WEB</ad:ad-source-id><ad:ad-external-reference-id/><ad:phone>571 288-1100</ad:phone><ad:view-ad-count>14</ad:view-ad-count><ad:prohibited-flag-count>0</ad:prohibited-flag-count><ad:spam-flag-count>0</ad:spam-flag-count><ad:miscategorized-flag-count>0</ad:miscategorized-flag-count><ad:creation-date-time>2011-07-05T20:14:35.000-07:00</ad:creation-date-time><ad:modification-date-time>2012-02-02T10:09:18.000-08:00</ad:modification-date-time><ad:start-date-time>2012-02-02T10:09:15.000-08:00</ad:start-date-time><ad:end-date-time>2012-04-02T11:09:15.000-07:00</ad:end-date-time><cat:category id="100143"><cat:localized-name>Events &amp; occasions</cat:localized-name></cat:category><loc:locations><loc:location id="2600308"><loc:id-name>frederick</loc:id-name><loc:localized-name>Frederick</loc:localized-name><loc:longitude>-77.34033</loc:longitude><loc:latitude>39.433086</loc:latitude><loc:regions localized-label="State"><loc:region><loc:localized-name>Maryland</loc:localized-name></loc:region><loc:region><loc:localized-name>Virginia</loc:localized-name></loc:region><loc:region><loc:localized-name>West Virginia</loc:localized-name></loc:region><loc:region><loc:localized-name>Pennsylvania</loc:localized-name></loc:region></loc:regions></loc:location><loc:location id="2600274"><loc:id-name>washingtondc</loc:id-name><loc:localized-name>Washington DC</loc:localized-name><loc:longitude>-77.01322</loc:longitude><loc:latitude>38.913612</loc:latitude><loc:regions localized-label="State"><loc:region><loc:localized-name>District of Columbia</loc:localized-name></loc:region><loc:region><loc:localized-name>Virginia</loc:localized-name></loc:region><loc:region><loc:localized-name>Maryland</loc:localized-name></loc:region></loc:regions></loc:location></loc:locations><attr:attributes/><ad:link rel="self" href="http://webapi.ebayclassifieds.com/webapi/ads/12481583"/><ad:link rel="self-user" href="http://webapi.ebayclassifieds.com/webapi/users/245386/ads/12481583"/><ad:link rel="self-public-website" href="http://frederick.ebayclassifieds.com/events-occasions/manassas/foto-y-video-para-bodas/?ad=12481583"/><pic:pictures><pic:picture><pic:link rel="thumbnail" href="http://img1.classistatic.com/cps/po/110705/218r1/0040nd6_24.jpeg"/><pic:link rel="teaser" href="http://img1.classistatic.com/cps/po/110705/218r1/0040nd6_25.jpeg"/><pic:link rel="normal" href="http://img1.classistatic.com/cps/po/110705/218r1/0040nd6_26.jpeg"/><pic:link rel="large" href="http://img1.classistatic.com/cps/po/110705/218r1/0040nd6_27.jpeg"/><pic:link rel="extra-large" href="http://img1.classistatic.com/cps/po/110705/218r1/0040nd6_20.jpeg"/></pic:picture><pic:picture><pic:link rel="thumbnail" href="http://img1.classistatic.com/cps/po/110705/219r4/439788e_24.jpeg"/><pic:link rel="teaser" href="http://img1.classistatic.com/cps/po/110705/219r4/439788e_25.jpeg"/><pic:link rel="normal" href="http://img1.classistatic.com/cps/po/110705/219r4/439788e_26.jpeg"/><pic:link rel="large" href="http://img1.classistatic.com/cps/po/110705/219r4/439788e_27.jpeg"/><pic:link rel="extra-large" href="http://img1.classistatic.com/cps/po/110705/219r4/439788e_20.jpeg"/></pic:picture><pic:picture><pic:link rel="thumbnail" href="http://img1.classistatic.com/cps/po/110705/219r3/67995ma_24.jpeg"/><pic:link rel="teaser" href="http://img1.classistatic.com/cps/po/110705/219r3/67995ma_25.jpeg"/><pic:link rel="normal" href="http://img1.classistatic.com/cps/po/110705/219r3/67995ma_26.jpeg"/><pic:link rel="large" href="http://img1.classistatic.com/cps/po/110705/219r3/67995ma_27.jpeg"/><pic:link rel="extra-large" href="http://img1.classistatic.com/cps/po/110705/219r3/67995ma_20.jpeg"/></pic:picture><pic:picture><pic:link rel="thumbnail" href="http://img1.classistatic.com/cps/po/110705/219r7/13761e4_24.jpeg"/><pic:link rel="teaser" href="http://img1.classistatic.com/cps/po/110705/219r7/13761e4_25.jpeg"/><pic:link rel="normal" href="http://img1.classistatic.com/cps/po/110705/219r7/13761e4_26.jpeg"/><pic:link rel="large" href="http://img1.classistatic.com/cps/po/110705/219r7/13761e4_27.jpeg"/><pic:link rel="extra-large" href="http://img1.classistatic.com/cps/po/110705/219r7/13761e4_20.jpeg"/></pic:picture><pic:picture><pic:link rel="thumbnail" href="http://img1.classistatic.com/cps/po/110705/219r5/4727ga3_24.jpeg"/><pic:link rel="teaser" href="http://img1.classistatic.com/cps/po/110705/219r5/4727ga3_25.jpeg"/><pic:link rel="normal" href="http://img1.classistatic.com/cps/po/110705/219r5/4727ga3_26.jpeg"/><pic:link rel="large" href="http://img1.classistatic.com/cps/po/110705/219r5/4727ga3_27.jpeg"/><pic:link rel="extra-large" href="http://img1.classistatic.com/cps/po/110705/219r5/4727ga3_20.jpeg"/></pic:picture><pic:picture><pic:link rel="thumbnail" href="http://img1.classistatic.com/cps/po/110705/220r1/616193b_24.jpeg"/><pic:link rel="teaser" href="http://img1.classistatic.com/cps/po/110705/220r1/616193b_25.jpeg"/><pic:link rel="normal" href="http://img1.classistatic.com/cps/po/110705/220r1/616193b_26.jpeg"/><pic:link rel="large" href="http://img1.classistatic.com/cps/po/110705/220r1/616193b_27.jpeg"/><pic:link rel="extra-large" href="http://img1.classistatic.com/cps/po/110705/220r1/616193b_20.jpeg"/></pic:picture><pic:picture><pic:link rel="thumbnail" href="http://img1.classistatic.com/cps/po/110705/220r7/1276hll_24.jpeg"/><pic:link rel="teaser" href="http://img1.classistatic.com/cps/po/110705/220r7/1276hll_25.jpeg"/><pic:link rel="normal" href="http://img1.classistatic.com/cps/po/110705/220r7/1276hll_26.jpeg"/><pic:link rel="large" href="http://img1.classistatic.com/cps/po/110705/220r7/1276hll_27.jpeg"/><pic:link rel="extra-large" href="http://img1.classistatic.com/cps/po/110705/220r7/1276hll_20.jpeg"/></pic:picture><pic:picture><pic:link rel="thumbnail" href="http://img1.classistatic.com/cps/po/110705/220r1/35398b9_24.jpeg"/><pic:link rel="teaser" href="http://img1.classistatic.com/cps/po/110705/220r1/35398b9_25.jpeg"/><pic:link rel="normal" href="http://img1.classistatic.com/cps/po/110705/220r1/35398b9_26.jpeg"/><pic:link rel="large" href="http://img1.classistatic.com/cps/po/110705/220r1/35398b9_27.jpeg"/><pic:link rel="extra-large" href="http://img1.classistatic.com/cps/po/110705/220r1/35398b9_20.jpeg"/></pic:picture></pic:pictures><ad:contact-methods/></ad:ad>